daily_papers/__init__.py
daily_papers/cli.py
daily_papers/utils.py
daily_papers/engine/__init__.py
daily_papers/engine/summarize.py
daily_papers-0.0.2.dist-info/entry_points.txt
daily_papers-0.0.2.dist-info/WHEEL
daily_papers-0.0.2.dist-info/METADATA
daily_papers-0.0.2.dist-info/RECORD
