Metadata-Version: 2.1
Name: daily-papers
Version: 0.0.2
Summary: catch-up with recent happenings in AI
Author-email: Saurav Maheshkar <sauravvmaheshkar@gmail.com>
Requires-Python: >=3.8
Classifier: Development Status :: 5 - Production/Stable
Classifier: License :: OSI Approved :: MIT License
Classifier: Programming Language :: Python
Classifier: Programming Language :: Python :: 3.8
Classifier: Programming Language :: Python :: 3.9
Classifier: Programming Language :: Python :: 3.10
Classifier: Programming Language :: Python :: 3.11
Classifier: Programming Language :: Python :: 3 :: Only
Requires-Dist: llama-index
Requires-Dist: llama-index-embeddings-huggingface
Requires-Dist: llama-index-llms-anthropic
Requires-Dist: python-dotenv
Requires-Dist: requests
Requires-Dist: rich
Requires-Dist: black ; extra == "dev"
Requires-Dist: isort ; extra == "dev"
Requires-Dist: mypy>=0.900 ; extra == "dev"
Requires-Dist: pre-commit>=2.18.0 ; extra == "dev"
Requires-Dist: pytest ; extra == "dev"
Requires-Dist: ruff ; extra == "dev"
Provides-Extra: dev
